MANIFEST.in
README.md
setup.py
salty/__init__.py
salty/core.py
salty/scraper.py
salty/version.py
salty/visualization.py
salty/data/Deslist
salty/data/anionDescriptors.csv
salty/data/anionInfo.csv
salty/data/cationDescriptors.csv
salty/data/cationInfo.csv
salty/data/cpt.csv
salty/data/cpt_density_desc.csv
salty/data/cpt_density_devmodel.pkl
salty/data/cpt_density_m1.sav
salty/data/cpt_density_m1_descriptors.csv
salty/data/cpt_density_m1_descriptors.csv~HEAD
salty/data/cpt_density_m1_descriptors.csv~mirrored master directory tree
salty/data/cpt_density_m1_summary.csv
salty/data/cpt_density_qspr.h5
salty/data/cpt_density_qspr.sav
salty/data/cpt_density_qspr_keras.sav
salty/data/cpt_density_summ.csv
salty/data/cpt_density_viscosity_devmodel.pkl
salty/data/cpt_desc.csv
salty/data/cpt_devmodel.pkl
salty/data/cpt_m1.sav
salty/data/cpt_m1_descriptors.csv
salty/data/cpt_m1_summary.csv
salty/data/cpt_premodel.csv
salty/data/cpt_qspr.h5
salty/data/cpt_qspr.sav
salty/data/cpt_summ.csv
salty/data/cpt_viscosity_density_devmodel.pkl
salty/data/cpt_viscosity_devmodel.pkl
salty/data/density.csv
salty/data/density_desc.csv
salty/data/density_devmodel.pkl
salty/data/density_m2.sav
salty/data/density_m2_descriptors.csv
salty/data/density_m3.sav
salty/data/density_m3_descriptors.csv
salty/data/density_m3_summary.csv
salty/data/density_m4.sav
salty/data/density_m4_descriptors.csv
salty/data/density_premodel.csv
salty/data/density_qspr.h5
salty/data/density_qspr.sav
salty/data/density_summ.csv
salty/data/electrical_conductivity.csv
salty/data/electrical_conductivity_premodel.csv
salty/data/melting_point.csv
salty/data/melting_point_premodel.csv
salty/data/thermal_conductivity.csv
salty/data/thermal_conductivity_desc.csv
salty/data/thermal_conductivity_premodel.csv
salty/data/thermal_conductivity_qspr.h5
salty/data/thermal_conductivity_summ.csv
salty/data/viscosity.csv
salty/data/viscosity_density_devmodel.pkl
salty/data/viscosity_density_m1.sav
salty_ilthermo.egg-info/PKG-INFO
salty_ilthermo.egg-info/SOURCES.txt
salty_ilthermo.egg-info/dependency_links.txt
salty_ilthermo.egg-info/requires.txt
salty_ilthermo.egg-info/top_level.txt