Metadata-Version: 1.1
Name: salty-ilthermo
Version: 0.2.dev17
Summary: An interactive data exploration tool for json structured ionic        liquid data from ILThermo (NIST)
Home-page: http://github.com/wesleybeckner/salty
Author: Wesley Beckner
Author-email: wesleybeckner@gmail.com
License: MIT
Platform: OS Independent
Classifier: Development Status :: 2 - Pre-Alpha
Classifier: Environment :: Console
Classifier: Intended Audience :: Science/Research
Classifier: License :: OSI Approved :: MIT License
Classifier: Operating System :: OS Independent
Classifier: Programming Language :: Python
Classifier: Topic :: Scientific/Engineering :: Information Analysis
Requires: numpy
